MANIFEST.in
README.md
setup.cfg
setup.py
src/TMultiplexedProcessor.py
src/TRecursive.py
src/TSCons.py
src/TSerialization.py
src/TTornado.py
src/Thrift.py
src/__init__.py
src/compat.py
src/ext/binary.cpp
src/ext/binary.h
src/ext/compact.cpp
src/ext/compact.h
src/ext/endian.h
src/ext/module.cpp
src/ext/protocol.h
src/ext/protocol.tcc
src/ext/types.cpp
src/ext/types.h
src/protocol/TBase.py
src/protocol/TBinaryProtocol.py
src/protocol/TCompactProtocol.py
src/protocol/THeaderProtocol.py
src/protocol/TJSONProtocol.py
src/protocol/TMultiplexedProtocol.py
src/protocol/TProtocol.py
src/protocol/TProtocolDecorator.py
src/protocol/__init__.py
src/server/THttpServer.py
src/server/TNonblockingServer.py
src/server/TProcessPoolServer.py
src/server/TServer.py
src/server/__init__.py
src/transport/THeaderTransport.py
src/transport/THttpClient.py
src/transport/TSSLSocket.py
src/transport/TSocket.py
src/transport/TTransport.py
src/transport/TTwisted.py
src/transport/TZlibTransport.py
src/transport/__init__.py
src/transport/sslcompat.py
test/test_socket.py
test/test_sslsocket.py
thrift_iomete.egg-info/PKG-INFO
thrift_iomete.egg-info/SOURCES.txt
thrift_iomete.egg-info/dependency_links.txt
thrift_iomete.egg-info/not-zip-safe
thrift_iomete.egg-info/requires.txt
thrift_iomete.egg-info/top_level.txt